indian_namematch/fuzzymatch.py
indian_namematch-1.3.0.dist-info/DESCRIPTION.rst
indian_namematch-1.3.0.dist-info/METADATA
indian_namematch-1.3.0.dist-info/RECORD
indian_namematch-1.3.0.dist-info/WHEEL
indian_namematch-1.3.0.dist-info/metadata.json
indian_namematch-1.3.0.dist-info/top_level.txt
