Metadata-Version: 2.0
Name: indian-namematch
Version: 1.3.0
Summary: Indian Fuzzy name Matching Tool.
Home-page: https://github.com/pypa/sampleproject
Author: Siddhesh Sharma
Author-email: siddheshatjuit@gmail.com
License: MIT
Platform: UNKNOWN
Classifier: Programming Language :: Python :: 3
Classifier: License :: OSI Approved :: MIT License
Classifier: Operating System :: OS Independent
Requires-Dist: nltk
Requires-Dist: pyphonetics
